streamlit_alert_component/__init__.py
streamlit_alert_component/frontend/build/asset-manifest.json
streamlit_alert_component/frontend/build/bootstrap.min.css
streamlit_alert_component/frontend/build/bootstrap.min.css.map
streamlit_alert_component/frontend/build/index.html
streamlit_alert_component/frontend/build/precache-manifest.192827bd19fdfd901fdf51777c8a404e.js
streamlit_alert_component/frontend/build/service-worker.js
streamlit_alert_component/frontend/build/static/js/2.4d0db124.chunk.js
streamlit_alert_component/frontend/build/static/js/2.4d0db124.chunk.js.LICENSE.txt
streamlit_alert_component/frontend/build/static/js/2.4d0db124.chunk.js.map
streamlit_alert_component/frontend/build/static/js/main.2f693818.chunk.js
streamlit_alert_component/frontend/build/static/js/main.2f693818.chunk.js.map
streamlit_alert_component/frontend/build/static/js/runtime-main.d31d2a75.js
streamlit_alert_component/frontend/build/static/js/runtime-main.d31d2a75.js.map
streamlit_alert_component-0.0.6.dist-info/LICENSE
streamlit_alert_component-0.0.6.dist-info/METADATA
streamlit_alert_component-0.0.6.dist-info/WHEEL
streamlit_alert_component-0.0.6.dist-info/top_level.txt
streamlit_alert_component-0.0.6.dist-info/RECORD
